gym_blocksudoku/__init__.py
gym_blocksudoku/envs/__init__.py
gym_blocksudoku/envs/blocksudoku_env.py
gym_blocksudoku-0.0.3.dist-info/LICENSE.md
gym_blocksudoku-0.0.3.dist-info/METADATA
gym_blocksudoku-0.0.3.dist-info/WHEEL
gym_blocksudoku-0.0.3.dist-info/top_level.txt
gym_blocksudoku-0.0.3.dist-info/RECORD
