Metadata-Version: 2.1
Name: gym-blocksudoku
Version: 0.0.3
Summary: OpenAI Gym Environment for Block Sudoku
Home-page: https://github.com/drakeor/gym-blocksudoku
Author: Drakeor
Author-email: me@drakeor.com
License: UNKNOWN
Platform: UNKNOWN
Requires-Dist: gym
Requires-Dist: numpy
